{
  "meta": {
    "symbol": "601857",
    "signal_type": "StaticGridSignal",
    "signal_params": {
      "lower_bound": 9.05,
      "upper_bound": 12.25,
      "n_levels": 20,
      "grid_type": "geometric",
      "cool_down_bars": 1,
      "reverse_order": false,
      "default_quantity": 100
    },
    "position_params": {
      "position_logic": {
        "quantity": 200,
        "mode": "grid_fixed"
      },
      "mode": "grid_manager",
      "cool_down": {
        "cool_down_bars": 1,
        "mode": "grid_cool_down"
      }
    },
    "initial_capital": 1000000.0,
    "fee_rate": 0.0003,
    "slippage_rate": 0.001,
    "tag": "walk_geome_n20_cd1_fixed_nosl_vt0.5",
    "config_key": "static_n20_geometric_fixed_cd1",
    "timestamp": "20260518_222633"
  },
  "result": {
    "config": {
      "start_date": "20260121",
      "end_date": "20260227",
      "initial_capital": 1000000.0,
      "fee_rate": 0.0003,
      "slippage_rate": 0.001
    },
    "actual_range": {
      "start": "20260121",
      "end": "20260227"
    },
    "total_bars": 22,
    "total_trades": 2,
    "trades": [
      {
        "date": "20260122",
        "symbol": "601857",
        "side": "buy",
        "price": 10.1601,
        "quantity": 200,
        "fee": 5.0,
        "slippage": 0.001,
        "order_type": "market"
      },
      {
        "date": "20260129",
        "symbol": "601857",
        "side": "sell",
        "price": 10.8791,
        "quantity": 200,
        "fee": 5.0,
        "slippage": 0.001,
        "order_type": "market"
      }
    ],
    "equity_curve": [
      {
        "date": "20260121",
        "total_equity": 1000000.0
      },
      {
        "date": "20260122",
        "total_equity": 999992.98
      },
      {
        "date": "20260123",
        "total_equity": 999928.98
      },
      {
        "date": "20260126",
        "total_equity": 1000040.98
      },
      {
        "date": "20260127",
        "total_equity": 1000050.98
      },
      {
        "date": "20260128",
        "total_equity": 1000116.98
      },
      {
        "date": "20260129",
        "total_equity": 1000133.8
      },
      {
        "date": "20260130",
        "total_equity": 1000133.8
      },
      {
        "date": "20260202",
        "total_equity": 1000133.8
      },
      {
        "date": "20260203",
        "total_equity": 1000133.8
      },
      {
        "date": "20260204",
        "total_equity": 1000133.8
      },
      {
        "date": "20260205",
        "total_equity": 1000133.8
      },
      {
        "date": "20260206",
        "total_equity": 1000133.8
      },
      {
        "date": "20260209",
        "total_equity": 1000133.8
      },
      {
        "date": "20260210",
        "total_equity": 1000133.8
      },
      {
        "date": "20260211",
        "total_equity": 1000133.8
      },
      {
        "date": "20260212",
        "total_equity": 1000133.8
      },
      {
        "date": "20260213",
        "total_equity": 1000133.8
      },
      {
        "date": "20260224",
        "total_equity": 1000133.8
      },
      {
        "date": "20260225",
        "total_equity": 1000133.8
      },
      {
        "date": "20260226",
        "total_equity": 1000133.8
      },
      {
        "date": "20260227",
        "total_equity": 1000133.8
      }
    ],
    "snapshots": [
      {
        "date": "20260121",
        "symbol": "601857",
        "capital": {
          "initial_capital": 1000000.0,
          "available": 1000000.0,
          "frozen": 0.0,
          "total_assets": 1000000.0
        },
        "positions": {},
        "position_market_value": 0.0,
        "total_equity": 1000000.0
      },
      {
        "date": "20260122",
        "symbol": "601857",
        "capital": {
          "initial_capital": 1000000.0,
          "available": 997962.98,
          "frozen": 0.0,
          "total_assets": 997962.98
        },
        "positions": {
          "601857": {
            "symbol": "601857",
            "quantity": 200,
            "avg_cost": 10.1851,
            "cost_basis": 2037.02,
            "market_value": 2030.0,
            "unrealized_pnl": -7.02,
            "lots": []
          }
        },
        "position_market_value": 2030.0,
        "total_equity": 999992.98
      },
      {
        "date": "20260123",
        "symbol": "601857",
        "capital": {
          "initial_capital": 1000000.0,
          "available": 997962.98,
          "frozen": 0.0,
          "total_assets": 997962.98
        },
        "positions": {
          "601857": {
            "symbol": "601857",
            "quantity": 200,
            "avg_cost": 10.1851,
            "cost_basis": 2037.02,
            "market_value": 1966.0,
            "unrealized_pnl": -71.02,
            "lots": []
          }
        },
        "position_market_value": 1966.0,
        "total_equity": 999928.98
      },
      {
        "date": "20260126",
        "symbol": "601857",
        "capital": {
          "initial_capital": 1000000.0,
          "available": 997962.98,
          "frozen": 0.0,
          "total_assets": 997962.98
        },
        "positions": {
          "601857": {
            "symbol": "601857",
            "quantity": 200,
            "avg_cost": 10.1851,
            "cost_basis": 2037.02,
            "market_value": 2078.0,
            "unrealized_pnl": 40.98,
            "lots": []
          }
        },
        "position_market_value": 2078.0,
        "total_equity": 1000040.98
      },
      {
        "date": "20260127",
        "symbol": "601857",
        "capital": {
          "initial_capital": 1000000.0,
          "available": 997962.98,
          "frozen": 0.0,
          "total_assets": 997962.98
        },
        "positions": {
          "601857": {
            "symbol": "601857",
            "quantity": 200,
            "avg_cost": 10.1851,
            "cost_basis": 2037.02,
            "market_value": 2088.0,
            "unrealized_pnl": 50.98,
            "lots": []
          }
        },
        "position_market_value": 2088.0,
        "total_equity": 1000050.98
      },
      {
        "date": "20260128",
        "symbol": "601857",
        "capital": {
          "initial_capital": 1000000.0,
          "available": 997962.98,
          "frozen": 0.0,
          "total_assets": 997962.98
        },
        "positions": {
          "601857": {
            "symbol": "601857",
            "quantity": 200,
            "avg_cost": 10.1851,
            "cost_basis": 2037.02,
            "market_value": 2154.0,
            "unrealized_pnl": 116.98,
            "lots": []
          }
        },
        "position_market_value": 2154.0,
        "total_equity": 1000116.98
      },
      {
        "date": "20260129",
        "symbol": "601857",
        "capital": {
          "initial_capital": 1000000.0,
          "available": 1000133.8,
          "frozen": 0.0,
          "total_assets": 1000133.8
        },
        "positions": {},
        "position_market_value": 0.0,
        "total_equity": 1000133.8
      },
      {
        "date": "20260130",
        "symbol": "601857",
        "capital": {
          "initial_capital": 1000000.0,
          "available": 1000133.8,
          "frozen": 0.0,
          "total_assets": 1000133.8
        },
        "positions": {},
        "position_market_value": 0.0,
        "total_equity": 1000133.8
      },
      {
        "date": "20260202",
        "symbol": "601857",
        "capital": {
          "initial_capital": 1000000.0,
          "available": 1000133.8,
          "frozen": 0.0,
          "total_assets": 1000133.8
        },
        "positions": {},
        "position_market_value": 0.0,
        "total_equity": 1000133.8
      },
      {
        "date": "20260203",
        "symbol": "601857",
        "capital": {
          "initial_capital": 1000000.0,
          "available": 1000133.8,
          "frozen": 0.0,
          "total_assets": 1000133.8
        },
        "positions": {},
        "position_market_value": 0.0,
        "total_equity": 1000133.8
      },
      {
        "date": "20260204",
        "symbol": "601857",
        "capital": {
          "initial_capital": 1000000.0,
          "available": 1000133.8,
          "frozen": 0.0,
          "total_assets": 1000133.8
        },
        "positions": {},
        "position_market_value": 0.0,
        "total_equity": 1000133.8
      },
      {
        "date": "20260205",
        "symbol": "601857",
        "capital": {
          "initial_capital": 1000000.0,
          "available": 1000133.8,
          "frozen": 0.0,
          "total_assets": 1000133.8
        },
        "positions": {},
        "position_market_value": 0.0,
        "total_equity": 1000133.8
      },
      {
        "date": "20260206",
        "symbol": "601857",
        "capital": {
          "initial_capital": 1000000.0,
          "available": 1000133.8,
          "frozen": 0.0,
          "total_assets": 1000133.8
        },
        "positions": {},
        "position_market_value": 0.0,
        "total_equity": 1000133.8
      },
      {
        "date": "20260209",
        "symbol": "601857",
        "capital": {
          "initial_capital": 1000000.0,
          "available": 1000133.8,
          "frozen": 0.0,
          "total_assets": 1000133.8
        },
        "positions": {},
        "position_market_value": 0.0,
        "total_equity": 1000133.8
      },
      {
        "date": "20260210",
        "symbol": "601857",
        "capital": {
          "initial_capital": 1000000.0,
          "available": 1000133.8,
          "frozen": 0.0,
          "total_assets": 1000133.8
        },
        "positions": {},
        "position_market_value": 0.0,
        "total_equity": 1000133.8
      },
      {
        "date": "20260211",
        "symbol": "601857",
        "capital": {
          "initial_capital": 1000000.0,
          "available": 1000133.8,
          "frozen": 0.0,
          "total_assets": 1000133.8
        },
        "positions": {},
        "position_market_value": 0.0,
        "total_equity": 1000133.8
      },
      {
        "date": "20260212",
        "symbol": "601857",
        "capital": {
          "initial_capital": 1000000.0,
          "available": 1000133.8,
          "frozen": 0.0,
          "total_assets": 1000133.8
        },
        "positions": {},
        "position_market_value": 0.0,
        "total_equity": 1000133.8
      },
      {
        "date": "20260213",
        "symbol": "601857",
        "capital": {
          "initial_capital": 1000000.0,
          "available": 1000133.8,
          "frozen": 0.0,
          "total_assets": 1000133.8
        },
        "positions": {},
        "position_market_value": 0.0,
        "total_equity": 1000133.8
      },
      {
        "date": "20260224",
        "symbol": "601857",
        "capital": {
          "initial_capital": 1000000.0,
          "available": 1000133.8,
          "frozen": 0.0,
          "total_assets": 1000133.8
        },
        "positions": {},
        "position_market_value": 0.0,
        "total_equity": 1000133.8
      },
      {
        "date": "20260225",
        "symbol": "601857",
        "capital": {
          "initial_capital": 1000000.0,
          "available": 1000133.8,
          "frozen": 0.0,
          "total_assets": 1000133.8
        },
        "positions": {},
        "position_market_value": 0.0,
        "total_equity": 1000133.8
      },
      {
        "date": "20260226",
        "symbol": "601857",
        "capital": {
          "initial_capital": 1000000.0,
          "available": 1000133.8,
          "frozen": 0.0,
          "total_assets": 1000133.8
        },
        "positions": {},
        "position_market_value": 0.0,
        "total_equity": 1000133.8
      },
      {
        "date": "20260227",
        "symbol": "601857",
        "capital": {
          "initial_capital": 1000000.0,
          "available": 1000133.8,
          "frozen": 0.0,
          "total_assets": 1000133.8
        },
        "positions": {},
        "position_market_value": 0.0,
        "total_equity": 1000133.8
      }
    ],
    "metrics": {
      "total_return_pct": 0.0134,
      "annual_return_pct": 0.1522,
      "max_drawdown": 71.02,
      "max_drawdown_pct": 0.0071,
      "calmar_ratio": 21.4237,
      "daily_returns": [
        -7.02e-06,
        -6.4e-05,
        0.00011201,
        1e-05,
        6.6e-05,
        1.682e-05,
        0.0,
        0.0,
        0.0,
        0.0,
        0.0,
        0.0,
        0.0,
        0.0,
        0.0,
        0.0,
        0.0,
        0.0,
        0.0,
        0.0,
        0.0
      ],
      "equity_curve": [
        {
          "date": "20260121",
          "total_equity": 1000000.0,
          "cumulative_return_pct": 0.0
        },
        {
          "date": "20260122",
          "total_equity": 999992.98,
          "cumulative_return_pct": -0.0007
        },
        {
          "date": "20260123",
          "total_equity": 999928.98,
          "cumulative_return_pct": -0.0071
        },
        {
          "date": "20260126",
          "total_equity": 1000040.98,
          "cumulative_return_pct": 0.0041
        },
        {
          "date": "20260127",
          "total_equity": 1000050.98,
          "cumulative_return_pct": 0.0051
        },
        {
          "date": "20260128",
          "total_equity": 1000116.98,
          "cumulative_return_pct": 0.0117
        },
        {
          "date": "20260129",
          "total_equity": 1000133.8,
          "cumulative_return_pct": 0.0134
        },
        {
          "date": "20260130",
          "total_equity": 1000133.8,
          "cumulative_return_pct": 0.0134
        },
        {
          "date": "20260202",
          "total_equity": 1000133.8,
          "cumulative_return_pct": 0.0134
        },
        {
          "date": "20260203",
          "total_equity": 1000133.8,
          "cumulative_return_pct": 0.0134
        },
        {
          "date": "20260204",
          "total_equity": 1000133.8,
          "cumulative_return_pct": 0.0134
        },
        {
          "date": "20260205",
          "total_equity": 1000133.8,
          "cumulative_return_pct": 0.0134
        },
        {
          "date": "20260206",
          "total_equity": 1000133.8,
          "cumulative_return_pct": 0.0134
        },
        {
          "date": "20260209",
          "total_equity": 1000133.8,
          "cumulative_return_pct": 0.0134
        },
        {
          "date": "20260210",
          "total_equity": 1000133.8,
          "cumulative_return_pct": 0.0134
        },
        {
          "date": "20260211",
          "total_equity": 1000133.8,
          "cumulative_return_pct": 0.0134
        },
        {
          "date": "20260212",
          "total_equity": 1000133.8,
          "cumulative_return_pct": 0.0134
        },
        {
          "date": "20260213",
          "total_equity": 1000133.8,
          "cumulative_return_pct": 0.0134
        },
        {
          "date": "20260224",
          "total_equity": 1000133.8,
          "cumulative_return_pct": 0.0134
        },
        {
          "date": "20260225",
          "total_equity": 1000133.8,
          "cumulative_return_pct": 0.0134
        },
        {
          "date": "20260226",
          "total_equity": 1000133.8,
          "cumulative_return_pct": 0.0134
        },
        {
          "date": "20260227",
          "total_equity": 1000133.8,
          "cumulative_return_pct": 0.0134
        }
      ],
      "sharpe_ratio": 3.2183,
      "volatility": 0.000495,
      "downside_volatility": 0.00045,
      "sortino_ratio": 3.536,
      "var_95_pct": -0.0007,
      "win_rate_pct": 100.0,
      "profit_loss_ratio": 0.0,
      "profit_factor": 999.99,
      "max_consecutive_wins": 1,
      "max_consecutive_losses": 0,
      "total_trades": 2,
      "final_equity": 1000133.8
    },
    "buy_hold_kpi": null
  }
}